{"128i": ["2 Dr Convertible", "2 Dr Coupe"], "135i": ["2 Dr Convertible", "2 Dr Coupe"], "323i": ["4 Dr Sedan"], "328i": ["2 Dr Convertible", "2 Dr Coupe", "4 Dr Sedan", "4 Dr Wagon"], "328xi": ["2 Dr Coupe", "4 Dr Sedan", "4 Dr Wagon"], "335i": ["2 Dr Convertible", "2 Dr Coupe", "4 Dr Sedan"], "335xi": ["2 Dr Coupe", "4 Dr Sedan"], "528i": ["4 Dr Sedan"], "528xi": ["4 Dr Sedan"], "535i": ["4 Dr Sedan"], "535xi": ["4 Dr Sedan", "4 Dr Wagon"], "550i": ["4 Dr Sedan"], "650i": ["2 Dr Convertible", "2 Dr Coupe"], "750Li": ["4 Dr Sedan"], "750i": ["4 Dr Sedan"], "760Li": ["4 Dr Sedan"], "Alpina B7": ["4 Dr Sedan"], "M3": ["2 Dr Convertible", "2 Dr Coupe", "4 Dr Sedan"], "M5": ["4 Dr Sedan"], "M6": ["2 Dr Convertible", "2 Dr Coupe"], "X3": ["4 Dr Sport Utility"], "X5": ["4 Dr Sport Utility"], "X6": ["4 Dr Sport Utility"], "Z4": ["2 Dr Convertible", "2 Dr Coupe"]}