{"Caravan": ["4 Dr Mini Passenger Van"], "Dakota": ["2 Dr Extended Cab Pickup, 5 Ft Bed", "2 Dr Extended Cab Pickup, 7 Ft Bed", "2 Dr Standard Cab Pickup, 5 Ft Bed", "2 Dr Standard Cab Pickup, 7 Ft Bed", "4 Dr Crew Cab Pickup, 5 Ft Bed", "4 Dr Crew Cab Pickup, 7 Ft Bed"], "Durango": ["4 Dr Sport Utility"], "Grand Caravan": ["4 Dr Mini Passenger Van"], "Intrepid": ["4 Dr Sedan"], "Neon": ["4 Dr Sedan"], "Ram 1500 Van": ["3 Dr Extended Cargo Van", "3 Dr Standard Cargo Van", "3 Dr Standard Passenger Van"], "Ram 1500": ["2 Dr Extended Cab Pickup, 6 Ft Bed", "2 Dr Extended Cab Pickup, 8 Ft Bed", "2 Dr Standard Cab Pickup, 6 Ft Bed", "2 Dr Standard Cab Pickup, 8 Ft Bed", "4 Dr Crew Cab Pickup, 6 Ft Bed", "4 Dr Crew Cab Pickup, 8 Ft Bed", "4 Dr Extended Cab Pickup, 6 Ft Bed", "4 Dr Extended Cab Pickup, 8 Ft Bed"], "Ram 2500 Van": ["3 Dr Extended Cargo Van", "3 Dr Standard Cargo Van", "3 Dr Standard Passenger Van"], "Ram 2500": ["2 Dr Cab & Chassis, 6 Ft Bed", "2 Dr Cab & Chassis, 8 Ft Bed", "2 Dr Extended Cab Pickup, 6 Ft Bed", "2 Dr Extended Cab Pickup, 8 Ft Bed", "2 Dr Standard Cab Pickup, 6 Ft Bed", "2 Dr Standard Cab Pickup, 8 Ft Bed", "4 Dr Extended Cab Pickup", "4 Dr Extended Cab Pickup, 6 Ft Bed", "4 Dr Extended Cab Pickup, 8 Ft Bed"], "Ram 3500 Van": ["3 Dr Extended Cargo Van", "3 Dr Extended Passenger Van", "3 Dr Standard Cargo Van"], "Ram 3500": ["2 Dr Cab & Chassis, 8 Ft Bed", "2 Dr Standard Cab Pickup, 8 Ft Bed", "4 Dr Extended Cab Pickup", "4 Dr Extended Cab Pickup, 8 Ft Bed"], "Stratus": ["2 Dr Coupe", "4 Dr Sedan"], "Viper": ["2 Dr Convertible", "2 Dr Coupe"]}